crisp/__init__.py
crisp/cache.py
crisp/cli.py
crisp/config.py
crisp/core.py
crisp/exceptions.py
crisp/file_selection.py
crisp/parsing.py
crisp/pre_commit.py
crisp/py.typed
crisp/pycodestyle.py
crisp/reporting.py
crisp/structures.py
ispras_crisp-0.2.0.dist-info/METADATA
ispras_crisp-0.2.0.dist-info/WHEEL
ispras_crisp-0.2.0.dist-info/entry_points.txt
ispras_crisp-0.2.0.dist-info/RECORD
